<?xml version="1.0" encoding="UTF-8"?>
<tv generator-info-name="Tempest EPG Generator (made by Kvanc)" generator-info-url="https://github.com/K-vanc/Tempest-EPG-Generator.git">
   <channel id="ESPN+ 1">
     <display-name lang="en">ESPN+ 1</display-name>
   </channel>
         <programme start="20260105020000 -0500" stop="20260105040000 -0500" channel="ESPN+ 1">
            <title lang="en">NFL PrimeTime on ESPN+</title>
         </programme>
   <channel id="ESPN+ 2">
     <display-name lang="en">ESPN+ 2</display-name>
   </channel>
         <programme start="20260105025500 -0500" stop="20260105045500 -0500" channel="ESPN+ 2">
            <title lang="en">Macarthur FC vs. Auckland FC</title>
         </programme>
   <channel id="ESPN+ 3">
     <display-name lang="en">ESPN+ 3</display-name>
   </channel>
         <programme start="20260105100000 -0500" stop="20260105120000 -0500" channel="ESPN+ 3">
            <title lang="en">Clinton &amp; Friends</title>
         </programme>
   <channel id="ESPN+ 4">
     <display-name lang="en">ESPN+ 4</display-name>
   </channel>
         <programme start="20260105110000 -0500" stop="20260105130000 -0500" channel="ESPN+ 4">
            <title lang="en">UTSA Women&#x27;s Basketball Presser</title>
         </programme>
   <channel id="ESPN+ 5">
     <display-name lang="en">ESPN+ 5</display-name>
   </channel>
         <programme start="20260105120000 -0500" stop="20260105140000 -0500" channel="ESPN+ 5">
            <title lang="en">The Pat McAfee Show</title>
         </programme>
   <channel id="ESPN+ 6">
     <display-name lang="en">ESPN+ 6</display-name>
   </channel>
         <programme start="20260105120000 -0500" stop="20260105140000 -0500" channel="ESPN+ 6">
            <title lang="en">Mon, 1/5 - The Rich Eisen Show</title>
         </programme>
   <channel id="ESPN+ 7">
     <display-name lang="en">ESPN+ 7</display-name>
   </channel>
         <programme start="20260105130000 -0500" stop="20260105150000 -0500" channel="ESPN+ 7">
            <title lang="en">UTSA Men&#x27;s Basketball Weekly Presser</title>
         </programme>
   <channel id="ESPN+ 8">
     <display-name lang="en">ESPN+ 8</display-name>
   </channel>
         <programme start="20260105150000 -0500" stop="20260105170000 -0500" channel="ESPN+ 8">
            <title lang="en">Freddie &amp; Harry</title>
         </programme>
   <channel id="ESPN+ 9">
     <display-name lang="en">ESPN+ 9</display-name>
   </channel>
         <programme start="20260105150000 -0500" stop="20260105170000 -0500" channel="ESPN+ 9">
            <title lang="en">Colorado New Athletic Director Press Conference</title>
         </programme>
   <channel id="ESPN+ 10">
     <display-name lang="en">ESPN+ 10</display-name>
   </channel>
         <programme start="20260105170000 -0500" stop="20260105190000 -0500" channel="ESPN+ 10">
            <title lang="en">Columbia vs. Cornell</title>
         </programme>
   <channel id="ESPN+ 11">
     <display-name lang="en">ESPN+ 11</display-name>
   </channel>
         <programme start="20260105170000 -0500" stop="20260105190000 -0500" channel="ESPN+ 11">
            <title lang="en">Brown vs. Yale</title>
         </programme>
   <channel id="ESPN+ 12">
     <display-name lang="en">ESPN+ 12</display-name>
   </channel>
         <programme start="20260105170000 -0500" stop="20260105190000 -0500" channel="ESPN+ 12">
            <title lang="en">Mon, 1/5 - ESPN FC</title>
         </programme>
   <channel id="ESPN+ 13">
     <display-name lang="en">ESPN+ 13</display-name>
   </channel>
         <programme start="20260105183000 -0500" stop="20260105203000 -0500" channel="ESPN+ 13">
            <title lang="en">Oakland vs. Youngstown State</title>
         </programme>
   <channel id="ESPN+ 14">
     <display-name lang="en">ESPN+ 14</display-name>
   </channel>
         <programme start="20260105183000 -0500" stop="20260105203000 -0500" channel="ESPN+ 14">
            <title lang="en">Anaheim Ducks vs. Washington Capitals (Ducks Broadcast)</title>
         </programme>
   <channel id="ESPN+ 15">
     <display-name lang="en">ESPN+ 15</display-name>
   </channel>
         <programme start="20260105183000 -0500" stop="20260105203000 -0500" channel="ESPN+ 15">
            <title lang="en">Anaheim Ducks vs. Washington Capitals (Capitals Broadcast)</title>
         </programme>
   <channel id="ESPN+ 16">
     <display-name lang="en">ESPN+ 16</display-name>
   </channel>
         <programme start="20260105183000 -0500" stop="20260105203000 -0500" channel="ESPN+ 16">
            <title lang="en">Utah Mammoth vs. New York Rangers (Rangers Broadcast)</title>
         </programme>
   <channel id="ESPN+ 17">
     <display-name lang="en">ESPN+ 17</display-name>
   </channel>
         <programme start="20260105183000 -0500" stop="20260105203000 -0500" channel="ESPN+ 17">
            <title lang="en">Utah Mammoth vs. New York Rangers (Mammoth Broadcast)</title>
         </programme>
   <channel id="ESPN+ 18">
     <display-name lang="en">ESPN+ 18</display-name>
   </channel>
         <programme start="20260105184000 -0500" stop="20260105204000 -0500" channel="ESPN+ 18">
            <title lang="en">Auckland Aces vs. Otago Volts</title>
         </programme>
   <channel id="ESPN+ 19">
     <display-name lang="en">ESPN+ 19</display-name>
   </channel>
         <programme start="20260105190000 -0500" stop="20260105210000 -0500" channel="ESPN+ 19">
            <title lang="en">Lamar vs. SE Louisiana</title>
         </programme>
   <channel id="ESPN+ 20">
     <display-name lang="en">ESPN+ 20</display-name>
   </channel>
         <programme start="20260105190000 -0500" stop="20260105210000 -0500" channel="ESPN+ 20">
            <title lang="en">Milwaukee vs. Green Bay</title>
         </programme>
   <channel id="ESPN+ 21">
     <display-name lang="en">ESPN+ 21</display-name>
   </channel>
         <programme start="20260105190000 -0500" stop="20260105210000 -0500" channel="ESPN+ 21">
            <title lang="en">Dartmouth vs. Harvard</title>
         </programme>
   <channel id="ESPN+ 22">
     <display-name lang="en">ESPN+ 22</display-name>
   </channel>
         <programme start="20260105190000 -0500" stop="20260105210000 -0500" channel="ESPN+ 22">
            <title lang="en">Pennsylvania vs. Princeton</title>
         </programme>
   <channel id="ESPN+ 23">
     <display-name lang="en">ESPN+ 23</display-name>
   </channel>
         <programme start="20260105190000 -0500" stop="20260105210000 -0500" channel="ESPN+ 23">
            <title lang="en">Yale vs. Brown</title>
         </programme>
   <channel id="ESPN+ 24">
     <display-name lang="en">ESPN+ 24</display-name>
   </channel>
         <programme start="20260105190000 -0500" stop="20260105210000 -0500" channel="ESPN+ 24">
            <title lang="en">IU Indianapolis vs. Purdue Fort Wayne</title>
         </programme>
   <channel id="ESPN+ 25">
     <display-name lang="en">ESPN+ 25</display-name>
   </channel>
         <programme start="20260105190000 -0500" stop="20260105210000 -0500" channel="ESPN+ 25">
            <title lang="en">Detroit Red Wings vs. Ottawa Senators (National Broadcast)</title>
         </programme>
   <channel id="ESPN+ 26">
     <display-name lang="en">ESPN+ 26</display-name>
   </channel>
         <programme start="20260105190000 -0500" stop="20260105210000 -0500" channel="ESPN+ 26">
            <title lang="en">Detroit Red Wings vs. Ottawa Senators (Red Wings Broadcast)</title>
         </programme>
   <channel id="ESPN+ 27">
     <display-name lang="en">ESPN+ 27</display-name>
   </channel>
         <programme start="20260105193000 -0500" stop="20260105213000 -0500" channel="ESPN+ 27">
            <title lang="en">Northwestern State vs. Nicholls</title>
         </programme>
   <channel id="ESPN+ 28">
     <display-name lang="en">ESPN+ 28</display-name>
   </channel>
         <programme start="20260105193000 -0500" stop="20260105213000 -0500" channel="ESPN+ 28">
            <title lang="en">Incarnate Word vs. UT Rio Grande Valley</title>
         </programme>
   <channel id="ESPN+ 29">
     <display-name lang="en">ESPN+ 29</display-name>
   </channel>
         <programme start="20260105193000 -0500" stop="20260105213000 -0500" channel="ESPN+ 29">
            <title lang="en">Stephen F. Austin vs. McNeese</title>
         </programme>
   <channel id="ESPN+ 30">
     <display-name lang="en">ESPN+ 30</display-name>
   </channel>
         <programme start="20260105200000 -0500" stop="20260105220000 -0500" channel="ESPN+ 30">
            <title lang="en">Texas A&amp;M-Corpus Christi vs. Houston Christian</title>
         </programme>
   <channel id="ESPN+ 31">
     <display-name lang="en">ESPN+ 31</display-name>
   </channel>
         <programme start="20260105200000 -0500" stop="20260105220000 -0500" channel="ESPN+ 31">
            <title lang="en">East Texas A&amp;M vs. New Orleans</title>
         </programme>
   <channel id="ESPN+ 32">
     <display-name lang="en">ESPN+ 32</display-name>
   </channel>
         <programme start="20260105210000 -0500" stop="20260105230000 -0500" channel="ESPN+ 32">
            <title lang="en">Seattle Kraken vs. Calgary Flames (Flames Broadcast)</title>
         </programme>
   <channel id="ESPN+ 33">
     <display-name lang="en">ESPN+ 33</display-name>
   </channel>
         <programme start="20260105210000 -0500" stop="20260105230000 -0500" channel="ESPN+ 33">
            <title lang="en">Seattle Kraken vs. Calgary Flames (Kraken Broadcast)</title>
         </programme>
   <channel id="ESPN+ 34">
     <display-name lang="en">ESPN+ 34</display-name>
   </channel>
         <programme start="20260105220000 -0500" stop="20260105240000 -0500" channel="ESPN+ 34">
            <title lang="en">Minnesota Wild vs. Los Angeles Kings (Kings Broadcast)</title>
         </programme>
   <channel id="ESPN+ 35">
     <display-name lang="en">ESPN+ 35</display-name>
   </channel>
         <programme start="20260105220000 -0500" stop="20260105240000 -0500" channel="ESPN+ 35">
            <title lang="en">Minnesota Wild vs. Los Angeles Kings (Wild Broadcast)</title>
         </programme>
   <channel id="ESPN+ 36">
     <display-name lang="en">ESPN+ 36</display-name>
   </channel>
         <programme start="20260105223000 -0500" stop="20260105243000 -0500" channel="ESPN+ 36">
            <title lang="en">FCS Football Championship Trophy Presentation (Trophy Presentation)</title>
         </programme>
   <channel id="ESPN+ 37">
     <display-name lang="en">ESPN+ 37</display-name>
   </channel>
         <programme start="20260105225000 -0500" stop="20260105245000 -0500" channel="ESPN+ 37">
            <title lang="en">Auckland Hearts vs. Otago Sparks</title>
         </programme>
</tv>
